{"page_36": [{"blocks": [{"polygon": [[68.25, 60.45], [1519.05, 60.45], [1519.05, 1729.65], [68.25, 1729.65]], "confidence": 0.9890526186903815, "label": "Table", "raw_label": "Table", "reading_order": 0, "html": "<table border=\"1\">\n<thead>\n<tr>\n<th>వరుస సంఖ్య.</th>\n<th>ఇంటి నం.</th>\n<th>ఓటరు పేరు</th>\n<th>బంధుత్వం</th>\n<th>బంధుత్వం పేరు</th>\n<th>స్త్రీ మరియు పురుష వైబేధం</th>\n<th>వయసు</th>\n<th>ఓటరు ఫోటో గుర్తింపు కార్డు నంబర్</th>\n</tr>\n<tr>\n<th>(1)</th>\n<th>(2)</th>\n<th>(3)</th>\n<th>(4)</th>\n<th>(5)</th>\n<th>(6)</th>\n<th>(7)</th>\n<th>(8)</th>\n</tr>\n</thead>\n<tbody>\n<tr>\n<td>681</td>\n<td>52-2</td>\n<td>రామసుబ్బమ్మ బత్తిన</td>\n<td>భ</td>\n<td>రఘునాధరెడ్డి</td>\n<td>స్త్రీ</td>\n<td>54</td>\n<td>AP221520222221</td>\n</tr>\n<tr>\n<td>682</td>\n<td>52-2</td>\n<td>ఆదిలక్ష్మి బత్తిన</td>\n<td>తం</td>\n<td>రఘునాధరెడ్డి</td>\n<td>స్త్రీ</td>\n<td>29</td>\n<td>AP221520222220</td>\n</tr>\n<tr>\n<td>683</td>\n<td>52-2</td>\n<td>శాంతకుమారి బత్తిన</td>\n<td>తం</td>\n<td>రఘునాధరెడ్డి</td>\n<td>స్త్రీ</td>\n<td>27</td>\n<td>AP221520222219</td>\n</tr>\n<tr>\n<td>684</td>\n<td>52-2 B</td>\n<td>సుమన అల్లపు రెడ్డి</td>\n<td>తం</td>\n<td>సత్యనారాయణ రెడ్డి</td>\n<td>స్త్రీ</td>\n<td>21</td>\n<td>AP221520000000</td>\n</tr>\n<tr>\n<td>685</td>\n<td>52-2 C</td>\n<td>విజయమ్మ అల్లం</td>\n<td>భ</td>\n<td>మల్ రెడ్డి</td>\n<td>స్త్రీ</td>\n<td>30</td>\n<td>AP221520000000</td>\n</tr>\n<tr>\n<td>686</td>\n<td>52-2 D</td>\n<td>సునీత నల్లపు రెడ్డి</td>\n<td>భ</td>\n<td>సురేష్ రెడ్డి</td>\n<td>స్త్రీ</td>\n<td>25</td>\n<td>AP221520000000</td>\n</tr>\n<tr>\n<td>687</td>\n<td>52-2 D-1</td>\n<td>ప్రేమలత కలక??డ</td>\n<td>భ</td>\n<td>నాగి రెడ్డి</td>\n<td>స్త్రీ</td>\n<td>45</td>\n<td>AP221520000000</td>\n</tr>\n<tr>\n<td>688</td>\n<td>52-2 D-2</td>\n<td>రెడ్డికుమారి వసంత</td>\n<td>భ</td>\n<td>రఘునాధ రెడ్డి</td>\n<td>స్త్రీ</td>\n<td>29</td>\n<td>AP221520000000</td>\n</tr>\n<tr>\n<td>689</td>\n<td>52-2 D-2-1</td>\n<td>క్రిష్ణవేణి పూజల</td>\n<td>భ</td>\n<td>రామయ్య</td>\n<td>స్త్రీ</td>\n<td>40</td>\n<td>AP221520000000</td>\n</tr>\n<tr>\n<td>690</td>\n<td>52-2 M</td>\n<td>వెంకటసుబ్బమ్మ హసనాపురం</td>\n<td>భ</td>\n<td>వెంకటరమణ</td>\n<td>స్త్రీ</td>\n<td>32</td>\n<td>AP221520000000</td>\n</tr>\n<tr>\n<td>691</td>\n<td>52-2 N</td>\n<td>వెంకటసుబ్బమ్మ పెట్లు</td>\n<td>భ</td>\n<td>నరసింహులు</td>\n<td>స్త్రీ</td>\n<td>55</td>\n<td>AP221520000000</td>\n</tr>\n<tr>\n<td>692</td>\n<td>52-2a</td>\n<td>పద్మావతి చిరసాల</td>\n<td>భ</td>\n<td>యోగాంజనేయులు</td>\n<td>స్త్రీ</td>\n<td>35</td>\n<td>AP221520222177</td>\n</tr>\n<tr>\n<td>693</td>\n<td>52-2a1</td>\n<td>పుల్లమ్మ జింకతోటి</td>\n<td>భ</td>\n<td>గుర్రన్న</td>\n<td>స్త్రీ</td>\n<td>54</td>\n<td>AP221520000000</td>\n</tr>\n<tr>\n<td>694</td>\n<td>52-2B</td>\n<td>అనుసూయమ్మ అల్లపు రెడ్డి</td>\n<td>భ</td>\n<td>సత్యనారాయణ రెడ్డి</td>\n<td>స్త్రీ</td>\n<td>40</td>\n<td>AP221520000000</td>\n</tr>\n<tr>\n<td>695</td>\n<td>52-2C</td>\n<td>రామలక్ష్మమమ్మ పద్మరాజు</td>\n<td>భ</td>\n<td>రఘురామరాజు</td>\n<td>స్త్రీ</td>\n<td>31</td>\n<td>AP221520000000</td>\n</tr>\n<tr>\n<td>696</td>\n<td>52-2C</td>\n<td>శంకరమ్మ పద్మరాజు</td>\n<td>భ</td>\n<td>బానుప్రకాష్ రాజు</td>\n<td>స్త్రీ</td>\n<td>21</td>\n<td>AP221520000000</td>\n</tr>\n<tr>\n<td>697</td>\n<td>52-2L</td>\n<td>దానమ్మ బుక్కే</td>\n<td>భ</td>\n<td>వాసుదేవనాయక్</td>\n<td>స్త్రీ</td>\n<td>25</td>\n<td>AP221520000000</td>\n</tr>\n<tr>\n<td>698</td>\n<td>52-4</td>\n<td>మంగమ్మ నౌరాగిరి</td>\n<td>భ</td>\n<td>చలమయ్య</td>\n<td>స్త్రీ</td>\n<td>47</td>\n<td>AP221520000000</td>\n</tr>\n<tr>\n<td>699</td>\n<td>52-6</td>\n<td>రాజమ్మ మేతకల</td>\n<td>భ</td>\n<td>పెంచయ్య</td>\n<td>స్త్రీ</td>\n<td>34</td>\n<td>AP221520000000</td>\n</tr>\n<tr>\n<td>700</td>\n<td>52-6-1</td>\n<td>లక్ష్మిదేవి మాది రెడ్డి</td>\n<td>భ</td>\n<td>గంగి రెడ్డి</td>\n<td>స్త్రీ</td>\n<td>38</td>\n<td>AP221520000000</td>\n</tr>\n</tbody>\n</table>", "skipped": false, "error": false, "bbox": [68.25, 60.45, 1519.05, 1729.65]}, {"polygon": [[70.19999999999999, 1780.3500000000001], [294.45, 1780.3500000000001], [294.45, 1815.45], [70.19999999999999, 1815.45]], "confidence": 0.9890526186903815, "label": "PageFooter", "raw_label": "Page-Footer", "reading_order": 1, "html": "<p>పుట సంఖ్య: 36 Of 59</p>", "skipped": false, "error": false, "bbox": [70.19999999999999, 1780.3500000000001, 294.45, 1815.45]}, {"polygon": [[399.75, 1774.5], [922.3499999999999, 1774.5], [922.3499999999999, 1809.6000000000001], [399.75, 1809.6000000000001]], "confidence": 0.9890526186903815, "label": "PageFooter", "raw_label": "Page-Footer", "reading_order": 2, "html": "<p>గడి సంఖ్య 4:-\"\"=ఇతరులు, \"తం\"-తండ్రి, \"త\"-తల్లి, \"భ\"-భర్త;</p>", "skipped": false, "error": false, "bbox": [399.75, 1774.5, 922.3499999999999, 1809.6000000000001]}, {"polygon": [[990.6, 1778.4], [1261.65, 1778.4], [1261.65, 1813.5], [990.6, 1813.5]], "confidence": 0.9890526186903815, "label": "PageFooter", "raw_label": "Page-Footer", "reading_order": 3, "html": "<p>గడి సంఖ్య 6:పు = పురుషుడు</p>", "skipped": false, "error": false, "bbox": [990.6, 1778.4, 1261.65, 1813.5]}, {"polygon": [[466.04999999999995, 1834.9499999999998], [836.55, 1834.9499999999998], [836.55, 1872.0], [466.04999999999995, 1872.0]], "confidence": 0.9890526186903815, "label": "PageFooter", "raw_label": "Page-Footer", "reading_order": 4, "html": "<p>శాసనసభ నియోజకవర్గం వర్గం సంఖ్య:152</p>", "skipped": false, "error": false, "bbox": [466.04999999999995, 1834.9499999999998, 836.55, 1872.0]}, {"polygon": [[990.6, 1834.9499999999998], [1177.8, 1834.9499999999998], [1177.8, 1868.1], [990.6, 1868.1]], "confidence": 0.9890526186903815, "label": "PageFooter", "raw_label": "Page-Footer", "reading_order": 5, "html": "<p>భాగం సంఖ్య: 77</p>", "skipped": false, "error": false, "bbox": [990.6, 1834.9499999999998, 1177.8, 1868.1]}], "image_bbox": [0.0, 0.0, 1950.0, 1950.0], "page": 1}]}